pytest_databases/__init__.py
pytest_databases/__metadata__.py
pytest_databases/_service.py
pytest_databases/helpers.py
pytest_databases/py.typed
pytest_databases/types.py
pytest_databases/docker/__init__.py
pytest_databases/docker/azure_blob.py
pytest_databases/docker/bigquery.py
pytest_databases/docker/cockroachdb.py
pytest_databases/docker/elastic_search.py
pytest_databases/docker/gizmosql.py
pytest_databases/docker/mariadb.py
pytest_databases/docker/minio.py
pytest_databases/docker/mongodb.py
pytest_databases/docker/mssql.py
pytest_databases/docker/mysql.py
pytest_databases/docker/oracle.py
pytest_databases/docker/postgres.py
pytest_databases/docker/redis.py
pytest_databases/docker/spanner.py
pytest_databases/docker/valkey.py
pytest_databases/docker/yugabyte.py
pytest_databases-0.16.0.dist-info/METADATA
pytest_databases-0.16.0.dist-info/WHEEL
pytest_databases-0.16.0.dist-info/entry_points.txt
pytest_databases-0.16.0.dist-info/licenses/LICENSE
pytest_databases-0.16.0.dist-info/RECORD
