Metadata-Version: 2.4
Name: pytest-databases
Version: 0.16.0
Summary: Reusable database fixtures for any and all databases.
Project-URL: Documentation, https://github.com/litestar-org/pytest-databases#readme
Project-URL: Issues, https://github.com/litestar-org/pytest-databases/issues
Project-URL: Source, https://github.com/litestar-org/pytest-databases
Author-email: Cody Fincher <cody@litestar.dev>
License-Expression: MIT
License-File: LICENSE
Keywords: alloydb,alloydbomni,azure,bigquery,cockroachdb,database,dragonflydb,duckdb,elasticsearch,flightsql,gizmosql,migration,mongodb,mssql,mysql,oracle,postgres,redis,spanner,valkey
Classifier: Development Status :: 4 - Beta
Classifier: Programming Language :: Python
Classifier: Programming Language :: Python :: 3.9
Classifier: Programming Language :: Python :: 3.10
Classifier: Programming Language :: Python :: 3.11
Classifier: Programming Language :: Python :: 3.12
Classifier: Programming Language :: Python :: 3.13
Classifier: Programming Language :: Python :: Implementation :: CPython
Classifier: Programming Language :: Python :: Implementation :: PyPy
Requires-Python: >=3.9
Requires-Dist: docker
Requires-Dist: filelock
Requires-Dist: pytest
Provides-Extra: azure-storage
Requires-Dist: azure-storage-blob; extra == 'azure-storage'
Provides-Extra: bigquery
Requires-Dist: google-cloud-bigquery; extra == 'bigquery'
Provides-Extra: cockroachdb
Requires-Dist: psycopg; extra == 'cockroachdb'
Provides-Extra: dragonfly
Requires-Dist: redis; extra == 'dragonfly'
Provides-Extra: elasticsearch7
Requires-Dist: elasticsearch7; extra == 'elasticsearch7'
Provides-Extra: elasticsearch8
Requires-Dist: elasticsearch8; extra == 'elasticsearch8'
Provides-Extra: gizmosql
Requires-Dist: adbc-driver-flightsql; extra == 'gizmosql'
Requires-Dist: pyarrow; extra == 'gizmosql'
Provides-Extra: keydb
Requires-Dist: redis; extra == 'keydb'
Provides-Extra: mariadb
Requires-Dist: mariadb; extra == 'mariadb'
Provides-Extra: minio
Requires-Dist: minio; extra == 'minio'
Provides-Extra: mongodb
Requires-Dist: pymongo; extra == 'mongodb'
Provides-Extra: mssql
Requires-Dist: pymssql; extra == 'mssql'
Provides-Extra: mysql
Requires-Dist: mysql-connector-python; extra == 'mysql'
Provides-Extra: oracle
Requires-Dist: oracledb; extra == 'oracle'
Provides-Extra: postgres
Requires-Dist: psycopg>=3; extra == 'postgres'
Provides-Extra: redis
Requires-Dist: redis; extra == 'redis'
Provides-Extra: spanner
Requires-Dist: google-cloud-spanner; extra == 'spanner'
Provides-Extra: valkey
Requires-Dist: valkey; extra == 'valkey'
Provides-Extra: yugabyte
Requires-Dist: psycopg2-yugabytedb; extra == 'yugabyte'
